odoo/addons/mgmtsystem_review_objective/README.rst
odoo/addons/mgmtsystem_review_objective/__init__.py
odoo/addons/mgmtsystem_review_objective/__manifest__.py
odoo/addons/mgmtsystem_review_objective/i18n/it.po
odoo/addons/mgmtsystem_review_objective/i18n/mgmtsystem_review_objective.pot
odoo/addons/mgmtsystem_review_objective/models/__init__.py
odoo/addons/mgmtsystem_review_objective/models/mgmtsystem_review.py
odoo/addons/mgmtsystem_review_objective/readme/CONTRIBUTORS.md
odoo/addons/mgmtsystem_review_objective/readme/DESCRIPTION.md
odoo/addons/mgmtsystem_review_objective/static/description/icon.png
odoo/addons/mgmtsystem_review_objective/static/description/index.html
odoo/addons/mgmtsystem_review_objective/views/mgmtsystem_indicator_value.xml
odoo/addons/mgmtsystem_review_objective/views/mgmtsystem_review.xml
odoo_addon_mgmtsystem_review_objective-18.0.1.0.1.2.dist-info/METADATA
odoo_addon_mgmtsystem_review_objective-18.0.1.0.1.2.dist-info/WHEEL
odoo_addon_mgmtsystem_review_objective-18.0.1.0.1.2.dist-info/top_level.txt
odoo_addon_mgmtsystem_review_objective-18.0.1.0.1.2.dist-info/RECORD
